README.md
setup.cfg
setup.py
brqr/__init__.py
brqr/brcode.py
brqr.egg-info/PKG-INFO
brqr.egg-info/SOURCES.txt
brqr.egg-info/dependency_links.txt
brqr.egg-info/not-zip-safe
brqr.egg-info/top_level.txt