Metadata-Version: 1.0
Name: brqr
Version: 1.21
Summary: Extração de dados BR CODE
Home-page: https://github.com/alexandremulina/brqr
Author: Hudson Brendon
Author-email: alexandremulina@hotmail.com
License: MIT
Platform: UNKNOWN
